xfhir/__init__.py
xfhir/__version__.py
xfhir/cli.py
xfhir-0.0.2.dist-info/LICENSE
xfhir-0.0.2.dist-info/METADATA
xfhir-0.0.2.dist-info/WHEEL
xfhir-0.0.2.dist-info/entry_points.txt
xfhir-0.0.2.dist-info/top_level.txt
xfhir-0.0.2.dist-info/RECORD
