Metadata-Version: 2.1
Name: xfhir
Version: 0.0.2
Summary: XFHIR Python SDK
Home-page: https://xfhir.com
Author: Akello Health
Author-email: vijay@akellohealth.com
License: Apache 2.0
Keywords: package development template
Classifier: Development Status :: 4 - Beta
Classifier: Intended Audience :: Developers
Classifier: Programming Language :: Python :: 3.7
Requires-Python: >=3
License-File: LICENSE
Requires-Dist: typer
Requires-Dist: rich
Requires-Dist: requests
